streamlit_ollama/__init__.py
streamlit_ollama/api.py
streamlit_ollama-0.1.1.dist-info/licenses/LICENSE
streamlit_ollama-0.1.1.dist-info/METADATA
streamlit_ollama-0.1.1.dist-info/WHEEL
streamlit_ollama-0.1.1.dist-info/top_level.txt
streamlit_ollama-0.1.1.dist-info/RECORD
