Metadata-Version: 2.4
Name: streamlit-ollama
Version: 0.1.1
Summary: Streamlit utilities for Ollama LLM integration
Home-page: https://github.com/yourusername/streamlit-ollama
Author: Your Name
Author-email: your.email@example.com
Classifier: Programming Language :: Python :: 3
Classifier: Operating System :: OS Independent
Classifier: Topic :: Software Development :: Libraries
Classifier: Topic :: Utilities
Requires-Python: >=3.7
License-File: LICENSE
Requires-Dist: streamlit>=1.0
Requires-Dist: requests>=2.25
Dynamic: author
Dynamic: author-email
Dynamic: classifier
Dynamic: description
Dynamic: description-content-type
Dynamic: home-page
Dynamic: license-file
Dynamic: requires-dist
Dynamic: requires-python
Dynamic: summary
